{
  "name": "Gliddd4 Repo",
  "identifier": "gliddd4.repo",
  "iconURL": "https://cdn1.realmzer.xyz/Untitled_Artwork-w6.png",
  "website": "https://discord.gg/hUK5m9MGFc",
  "subtitle": "Repository for @gliddd4's apps",
  "description": "Repository for @gliddd4 projects and compiled social media tweaks. ✅ = working, ❌ = not working.",
  "tintColor": "D3D5D4",
  "featuredApps": [
    "dummyapp",
    "com.gliddd4.realmzer.mysign"
  ],
  "apps": [
    {
      "beta": true,
      "name": "✅ MySign",
      "bundleIdentifier": "com.gliddd4.realmzer.mysign",
      "developerName": "gliddd4",
      "subtitle": "Initial release for MySign. 1.0",
      "description": "⚠️ Version 1.0 and below do not sideload. Please wait until 2.22.25 for MySign 2.0 to release.",
      "localizedDescription": "⚠️ Version 1.0 and below do not sideload. Please wait until 2.22.25 for MySign 2.0 to release.",
      "iconURL": "https://cdn1.realmzer.xyz/IMG_4153-UV.png",
      "tintColor": "#326B8B",
      "category": "utilities",
      "version": "1.0",
      "versionDate": "2024-12-26",
      "downloadURL": "https://cdn1.realmzer.xyz/My_Sign-5h.ipa",
      "size": 2860000,
      "title": "MySign",
      "url": "https://discord.gg/hUK5m9MGFc"
    },
    {
      "beta": true,
      "name": "✅ TrollTrollStore",
      "bundleIdentifier": "com.opa334.Trollstore",
      "developerName": "opa334",
      "subtitle": "TrollStore but instead of trolling Apple, you can troll people into thinking you have TrollStore",
      "description": "TrollStore but instead of trolling Apple, you can troll people into thinking you have TrollStore\nStatus: ✅🔥",
      "localizedDescription": "TrollStore but instead of trolling Apple, you can troll people into thinking you have TrollStore\nStatus: ✅🔥",
      "iconURL": "https://cdn1.realmzer.xyz/IMG_4095-FQ.jpeg",
      "tintColor": "#00BFFE",
      "category": "utilities",
      "version": "2.1",
      "versionDate": "2025-02-03",
      "downloadURL": "https://cdn1.realmzer.xyz/Troll_Troll_Store_My_Sign-Ra.ipa",
      "size": 3470000,
      "title": "TrollTrollStore",
      "url": "https://discord.gg/hUK5m9MGFc"
    },
    {
      "name": "✅ YTLite Full",
      "bundleIdentifier": "com.google.ios.youtube",
      "developerName": "SultanMods",
      "iconURL": "https://is1-ssl.mzstatic.com/image/thumb/Purple211/v4/5c/b1/e8/5cb1e895-95b4-3e92-d215-e98b1b21ec4b/logo_youtube_2024_q4_color-0-1x_U007emarketing-0-0-0-6-0-0-0-85-220-0.png/512x512bb.jpg",
      "version": "20.05.4",
      "size": 113014829,
      "downloadURL": "https://repo.sultanmods.fyi/355244b7-2659-4812-83ae-7d5c467d15d9/Youtube20.05.4YTLite5.1FullFeb3rdMoe.ipa",
      "localizedDescription": "YouTube 20.05.4 YTLite 5.1 Full Feb 2nd (turn off vp9 if you have a 15 pro or above)\n https://t.me/SultanModsiOS",
      "versionDate": "2025-02-02"
    },
    {
      "name": "Classic BHTwitter+",
      "bundleIdentifier": "com.atebits.Tweetie2",
      "developerName": "SultanMods",
      "iconURL": "https://is1-ssl.mzstatic.com/image/thumb/Purple211/v4/db/29/ce/db29ce93-44b8-deb4-75ea-1c3f8e7027a2/ProductionAppIcon-0-0-1x_U007emarketing-0-7-0-0-0-85-220.png/512x512bb.jpg",
      "version": "10.79.1",
      "size": 145580851,
      "downloadURL": "https://repo.sultanmods.fyi/de9a464b-9899-4b75-b1b4-86e00fe7632c/Classic_BHTwitter+_10.79.1_Jacks_Apps_Yellow.ipa",
      "localizedDescription": "Classic BHTwitter+ 10.79.1",
      "versionDate": "2025-02-05"
    },
  ],
  "news": [
    {
      "title": "Thanks for using my personal repository",
      "identifier": "joinourdcserver",
      "caption": "If you're interested in my projects, you can join my server by clicking this.",
      "date": "2025-01-28",
      "tintColor": "#326B8B",
      "imageURL": "https://cdn1.realmzer.xyz/IMG_4153-UV.png",
      "url": "https://discord.gg/hUK5m9MGFc",
      "notify": true
    }
  ]
}